FairDynamicRec-0.0.143.data/scripts/__main__.py
fair_dynamic_rec/.DS_Store
fair_dynamic_rec/__init__.py
fair_dynamic_rec/__main__.py
fair_dynamic_rec/cb1.txt
fair_dynamic_rec/cb2.txt
fair_dynamic_rec/core/.DS_Store
fair_dynamic_rec/core/__init__.py
fair_dynamic_rec/core/config_cmd.py
fair_dynamic_rec/core/data_cmd.py
fair_dynamic_rec/core/metric_cmd.py
fair_dynamic_rec/core/visualization_cmd.py
fair_dynamic_rec/core/rankers/.DS_Store
fair_dynamic_rec/core/rankers/abstract_ranker.py
fair_dynamic_rec/core/rankers/abstract_ranker.pyc
fair_dynamic_rec/core/rankers/ea_hybrid_lsb_linucb.py
fair_dynamic_rec/core/rankers/ea_hybrid_lsb_linucb_itemweighting.py
fair_dynamic_rec/core/rankers/ea_linear_submodular_bandit.py
fair_dynamic_rec/core/rankers/ea_linear_submodular_bandit_itemweigting.py
fair_dynamic_rec/core/rankers/ea_linear_upper_confidence_bound.py
fair_dynamic_rec/core/rankers/ea_linear_upper_confidence_bound_itemweighting.py
fair_dynamic_rec/core/rankers/ears_hybrid_lsb_linucb.py
fair_dynamic_rec/core/rankers/ears_linear_submodular_bandit.py
fair_dynamic_rec/core/rankers/ears_linear_thompson_sampling.py
fair_dynamic_rec/core/rankers/ears_linear_upper_confidence_bound.py
fair_dynamic_rec/core/rankers/factor_ucb.py
fair_dynamic_rec/core/rankers/factor_ucb1.py
fair_dynamic_rec/core/rankers/factor_ucb2.py
fair_dynamic_rec/core/rankers/hybrid_lsb_linucb.py
fair_dynamic_rec/core/rankers/hybrid_lsb_linucb_1.py
fair_dynamic_rec/core/rankers/kl_upper_confidence_bound.py
fair_dynamic_rec/core/rankers/linear_neighbor_bandit.py
fair_dynamic_rec/core/rankers/linear_neighbor_bandit1.py
fair_dynamic_rec/core/rankers/linear_neighbor_bandit3.py
fair_dynamic_rec/core/rankers/linear_submodular_bandit.py
fair_dynamic_rec/core/rankers/linear_submodular_bandit_1.py
fair_dynamic_rec/core/rankers/linear_submodular_bandit_2.py
fair_dynamic_rec/core/rankers/linear_upper_confidence_bound.py
fair_dynamic_rec/core/rankers/linear_upper_confidence_bound_1.py
FairDynamicRec-0.0.143.dist-info/METADATA
FairDynamicRec-0.0.143.dist-info/WHEEL
FairDynamicRec-0.0.143.dist-info/top_level.txt
FairDynamicRec-0.0.143.dist-info/RECORD
