Metadata-Version: 2.1
Name: FairDynamicRec
Version: 0.0.143
Summary: The FairDynamicRec project aims to facilitate recommender system experiments in dynamic setting where system is operating over time.
Home-page: UNKNOWN
Author: Masoud Mansoury
Author-email: masoodmansoury@gmail.com
License: UNKNOWN
Platform: UNKNOWN
Classifier: Programming Language :: Python :: 3
Classifier: License :: OSI Approved :: MIT License
Classifier: Operating System :: OS Independent
Requires-Dist: matplotlib
Requires-Dist: pandas
Requires-Dist: numpy
Requires-Dist: lxml
Requires-Dist: scipy
Requires-Dist: tqdm
Requires-Dist: joblib
